{
  "type": "minecraft:chest",
  "pools": [
    {
      "bonus_rolls": 0,
      "entries": [
        {
          "type": "minecraft:item",
          "name": "minecraft:diamond",
          "weight": 1,
          "conditions": [],
          "functions": [
            {
              "function": "minecraft:set_count",
              "count": {
                "type": "minecraft:uniform",
                "min": 5,
                "max": 6
              }
            }
          ]
        },
        {
          "type": "minecraft:item",
          "name": "cosmic_veil:shadrock_nugget",
          "weight": 5,
          "functions": [
            {
              "function": "minecraft:set_count",
              "count": {
                "type": "minecraft:uniform",
                "min": 4,
                "max": 7
              }
            }
          ]
        },
        {
          "type": "minecraft:item",
          "name": "cosmic_veil:eclipsium_nugget",
          "weight": 10,
          "conditions": [],
          "functions": [
            {
              "function": "minecraft:set_count",
              "count": {
                "type": "minecraft:uniform",
                "min": 6,
                "max": 10
              }
            }
          ]
        },
        {
          "type": "minecraft:item",
          "name": "cosmic_veil:ashenite",
          "weight": 3,
          "functions": [
            {
              "function": "minecraft:set_count",
              "count": {
                "type": "minecraft:uniform",
                "min": 4,
                "max": 7
              }
            }
          ]
        },
        {
          "type": "minecraft:item",
          "name": "minecraft:book",
          "weight": 10,
          "functions": [
            {
              "function": "minecraft:enchant_with_levels",
              "levels": 30,
              "treasure": true
            }
          ]
        },
        {
          "type": "minecraft:item",
          "name": "minecraft:ancient_debris",
          "weight": 3,
          "functions": [
            {
              "function": "minecraft:set_count",
              "count": {
                "type": "minecraft:uniform",
                "min": 1,
                "max": 4
              }
            }
          ]
        },
        {
          "type": "minecraft:item",
          "name": "cosmic_veil:dark_shadow_rock",
          "weight": 3,
          "conditions": [],
          "functions": [
            {
              "function": "minecraft:set_count",
              "count": {
                "type": "minecraft:uniform",
                "min": 3,
                "max": 10
              }
            }
          ]
        },
        {
          "type": "minecraft:item",
          "name": "cosmic_veil:red_shadow_rock",
          "weight": 3,
          "functions": [
            {
              "function": "minecraft:set_count",
              "count": {
                "type": "minecraft:uniform",
                "min": 3,
                "max": 10
              }
            }
          ]
        },
        {
          "type": "minecraft:item",
          "name": "cosmic_veil:light_shadow_rock",
          "weight": 3,
          "functions": [
            {
              "function": "minecraft:set_count",
              "count": {
                "type": "minecraft:uniform",
                "min": 3,
                "max": 10
              }
            }
          ]
        },
        {
          "type": "minecraft:item",
          "name": "cosmic_veil:shadow_trap",
          "weight": 1,
          "functions": [
            {
              "function": "minecraft:set_count",
              "count": {
                "type": "minecraft:uniform",
                "min": 3,
                "max": 10
              }
            }
          ]
        },
        {
          "type": "minecraft:item",
          "name": "cosmic_veil:weeper_totem",
          "weight": 1,
          "functions": [
            {
              "function": "minecraft:set_count",
              "count": 1
            }
          ]
        }
      ],
      "rolls": {
        "type": "minecraft:uniform",
        "min": 4,
        "max": 8
      },
      "functions": [],
      "conditions": []
    },
    {
      "rolls": 1,
      "entries": [
        {
          "type": "minecraft:item",
          "name": "cosmic_veil:shadow_imbuer",
          "weight": 1,
          "conditions": [
            {
              "condition": "minecraft:random_chance",
              "chance": 0.1
            }
          ]
        }
      ]
    }
  ],
  "functions": []
}